helloPackage/HelloYahya.py
helloPackage/__init__.py
helloyahyaali-0.0.1.dist-info/METADATA
helloyahyaali-0.0.1.dist-info/WHEEL
helloyahyaali-0.0.1.dist-info/top_level.txt
helloyahyaali-0.0.1.dist-info/RECORD
