Metadata-Version: 2.1
Name: helloyahyaali
Version: 0.0.1
Summary: Saying hi to Yahya
Author: Yahya Ali
Author-email: yahya.ali97@outlook.com
Keywords: python
Classifier: Development Status :: 1 - Planning
Classifier: Intended Audience :: Developers
Classifier: Programming Language :: Python :: 3
Classifier: Operating System :: Unix
Classifier: Operating System :: MacOS :: MacOS X
Classifier: Operating System :: Microsoft :: Windows
